mdplain/__init__.py
mdplain-1.0.dist-info/LICENCE
mdplain-1.0.dist-info/METADATA
mdplain-1.0.dist-info/WHEEL
mdplain-1.0.dist-info/top_level.txt
mdplain-1.0.dist-info/RECORD
