Metadata-Version: 2.1
Name: mdplain
Version: 1.0
Summary: convert markdown to plain text
Home-page: https://github.com/icaijy/mdplain
Author: caijunyi
Author-email: caijunyi08@outlook.com
License: MIT License
Platform: UNKNOWN
Classifier: Programming Language :: Python :: 3
Requires-Dist: beautifulsoup4
Requires-Dist: markdown
